pokercraft_local-2.3.0.dist-info/METADATA
pokercraft_local-2.3.0.dist-info/WHEEL
pokercraft_local-2.3.0.dist-info/licenses/LICENSE
pokercraft_local/__init__.py
pokercraft_local/constants.py
pokercraft_local/data_structures.py
pokercraft_local/export.py
pokercraft_local/gui.py
pokercraft_local/hu_preflop_cache.txt.gz
pokercraft_local/parser.py
pokercraft_local/py.typed
pokercraft_local/pypi_query.py
pokercraft_local/rust.cpython-313t-s390x-linux-gnu.so
pokercraft_local/rust/__init__.pyi
pokercraft_local/rust/bankroll.pyi
pokercraft_local/rust/card.pyi
pokercraft_local/rust/equity.pyi
pokercraft_local/translate.py
pokercraft_local/translation_values.json
pokercraft_local/utils.py
pokercraft_local/visualize/__init__.py
pokercraft_local/visualize/hand_history.py
pokercraft_local/visualize/tourney_summary.py
pokercraft_local-2.3.0.dist-info/RECORD
