Metadata-Version: 2.4
Name: pokercraft-local
Version: 2.3.0
Classifier: Programming Language :: Python :: 3
Classifier: License :: OSI Approved :: MIT License
Classifier: Development Status :: 4 - Beta
Classifier: Operating System :: OS Independent
Classifier: Topic :: Games/Entertainment :: Turn Based Strategy
Classifier: Topic :: Scientific/Engineering :: Visualization
Classifier: Topic :: Software Development :: Libraries
Classifier: Typing :: Typed
Requires-Dist: pandas==2.2.*
Requires-Dist: plotly==5.24.*
Requires-Dist: statsmodels==0.14.*
Requires-Dist: markdown==3.7.*
Requires-Dist: forex-python==1.8.*
Requires-Dist: requests==2.32.*
License-File: LICENSE
Summary: Local analysis tool for Pokercraft in GGNetwork
Keywords: poker,pokercraft,ggpoker
Author-email: Minsung Kim <spongbob9876@naver.com>
Requires-Python: >=3.12
Project-URL: Homepage, https://github.com/McDic/pokercraft-local
